moruapp_ms_sso/__init__.c
moruapp_ms_sso/__init__.cp313-win_amd64.pyd
moruapp_ms_sso/__init__.cpython-312-x86_64-linux-gnu.so
moruapp_ms_sso/__main__.c
moruapp_ms_sso/__main__.cp313-win_amd64.pyd
moruapp_ms_sso/__main__.cpython-312-x86_64-linux-gnu.so
moruapp_ms_sso/config.c
moruapp_ms_sso/config.cp313-win_amd64.pyd
moruapp_ms_sso/config.cpython-312-x86_64-linux-gnu.so
moruapp_ms_sso/sso.c
moruapp_ms_sso/sso.cp313-win_amd64.pyd
moruapp_ms_sso/sso.cpython-312-x86_64-linux-gnu.so
moruapp_ms_sso-0.1.16.dist-info/licenses/LICENSE
moruapp_ms_sso-0.1.16.dist-info/METADATA
moruapp_ms_sso-0.1.16.dist-info/WHEEL
moruapp_ms_sso-0.1.16.dist-info/top_level.txt
moruapp_ms_sso-0.1.16.dist-info/RECORD
