Metadata-Version: 2.4
Name: moruapp-ms-sso
Version: 0.1.16
Summary: FastAPI extension: Microsoft SSO via fastapi-sso
Home-page: https://github.com/you/moruapp-ms-sso
Author: MoruApp
Author-email: MoruApp <you@example.com>
License: MIT
Project-URL: Homepage, https://github.com/you/moruapp-ms-sso
Project-URL: Repository, https://github.com/you/moruapp-ms-sso.git
Classifier: License :: OSI Approved :: MIT License
Classifier: Programming Language :: Python :: 3
Classifier: Programming Language :: Python :: 3.8
Classifier: Framework :: FastAPI
Requires-Python: >=3.8
License-File: LICENSE
Requires-Dist: fastapi>=0.95
Requires-Dist: uvicorn
Requires-Dist: fastapi-sso
Requires-Dist: python-dotenv
Requires-Dist: pydantic-settings
Requires-Dist: PyJWT
Dynamic: license-file
